lib_version_URLPhishing/__init__.py
lib_version_URLPhishing/version.py
lib_version_URLPhishing/version_util.py
lib_version_urlphishing-2.9.7.dist-info/METADATA
lib_version_urlphishing-2.9.7.dist-info/WHEEL
lib_version_urlphishing-2.9.7.dist-info/RECORD
